michina/checks/__init__.py
michina/checks/base/check.py
michina/checks/consistency/__init__.py
michina/checks/consistency/check.py
michina/checks/consistency/prompt.py
michina/checks/tone/__init__.py
michina/checks/tone/check.py
michina/checks/tone/prompt.py
michina/exceptions/exceptions.py
michina-0.2.2.dist-info/METADATA
michina-0.2.2.dist-info/WHEEL
michina-0.2.2.dist-info/RECORD
